[
  {
    "symbol": "HAYL.N0000",
    "company": "HAYLEYS PLC",
    "revenue": null,
    "net_income": null,
    "eps": null,
    "operating_profit": null,
    "ebitda": null,
    "fetched_at": "2026-04-27T00:02:55.589827Z"
  },
  {
    "symbol": "HAYL.N0000",
    "company": "HAYLEYS PLC",
    "revenue": null,
    "net_income": null,
    "eps": null,
    "operating_profit": null,
    "ebitda": null,
    "fetched_at": "2026-04-27T04:05:46.957655Z"
  },
  {
    "symbol": "HAYL.N0000",
    "company": "HAYLEYS PLC",
    "revenue": null,
    "net_income": null,
    "eps": null,
    "operating_profit": null,
    "ebitda": null,
    "fetched_at": "2026-04-27T07:12:46.477688Z"
  },
  {
    "symbol": "HAYL.N0000",
    "company": "HAYLEYS PLC",
    "revenue": null,
    "net_income": null,
    "eps": null,
    "operating_profit": null,
    "ebitda": null,
    "fetched_at": "2026-04-27T09:36:23.578350Z"
  }
]
