[
  {
    "symbol": "HAYL.N0000",
    "company": "HAYLEYS PLC",
    "beta": {
      "triASI": 0.9004329,
      "SPSL": 0.8157314,
      "period": "2025",
      "quarter": 1
    },
    "pe_ratio": null,
    "pb_ratio": null,
    "dividend_yield": null,
    "fetched_at": "2026-04-24T02:09:22.581149Z"
  },
  {
    "symbol": "HAYL.N0000",
    "company": "HAYLEYS PLC",
    "beta": {
      "triASI": 0.9004329,
      "SPSL": 0.8157314,
      "period": "2025",
      "quarter": 1
    },
    "pe_ratio": null,
    "pb_ratio": null,
    "dividend_yield": null,
    "fetched_at": "2026-04-24T05:20:27.421190Z"
  },
  {
    "symbol": "HAYL.N0000",
    "company": "HAYLEYS PLC",
    "beta": {
      "triASI": 0.9004329,
      "SPSL": 0.8157314,
      "period": "2025",
      "quarter": 1
    },
    "pe_ratio": null,
    "pb_ratio": null,
    "dividend_yield": null,
    "fetched_at": "2026-04-24T07:16:15.521666Z"
  },
  {
    "symbol": "HAYL.N0000",
    "company": "HAYLEYS PLC",
    "beta": {
      "triASI": 0.9004329,
      "SPSL": 0.8157314,
      "period": "2025",
      "quarter": 1
    },
    "pe_ratio": null,
    "pb_ratio": null,
    "dividend_yield": null,
    "fetched_at": "2026-04-24T09:15:20.760213Z"
  }
]
